npsfm/__init__.py
npsfm/fenz_data_processing.py
npsfm/main.py
npsfm/params.py
npsfm/rec_data_processing.py
npsfm/utils.py
npsfm/v202401.py
npsfm/tests/__init__.py
npsfm/tests/test_data1.csv.zip
npsfm/tests/test_npsfm.py
npsfm-0.1.16.dist-info/METADATA
npsfm-0.1.16.dist-info/WHEEL
npsfm-0.1.16.dist-info/licenses/LICENSE
npsfm-0.1.16.dist-info/RECORD
