Metadata-Version: 2.4
Name: npsfm
Version: 0.1.16
Summary: Python package to estimate the grades for the nps-fm-2020
Project-URL: Documentation, https://mullenkamp.github.io/nps-fm-2020/
Project-URL: Source, https://github.com/nps-fm-2020
Author-email: Mike <mullenkamp1@gmail.com>
License-File: LICENSE
Classifier: Programming Language :: Python :: 3 :: Only
Requires-Python: >=3.10
Requires-Dist: booklet>=0.5.2
Requires-Dist: msgpack
Requires-Dist: pandas
Requires-Dist: urllib3>=2
